pyimgren/__init__.py
pyimgren/__main__.py
pyimgren/cmdline.py
pyimgren/renamer.py
pyimgren/version.py
pyimgren/locale/fr/LC_MESSAGES/cmdline.mo
pyimgren/locale/fr/LC_MESSAGES/pyimgren.mo
pyimgren-1.0.0.dist-info/METADATA
pyimgren-1.0.0.dist-info/WHEEL
pyimgren-1.0.0.dist-info/entry_points.txt
pyimgren-1.0.0.dist-info/licenses/LICENSE.txt
pyimgren-1.0.0.dist-info/RECORD
