Metadata-Version: 2.4
Name: pyimgren
Version: 1.0.0
Summary: Rename image files according to exif tags
Project-URL: Documentation, https://pyimgren.readthedocs.io/en/latest/
Project-URL: Changelog, https://github.com/s-ball/pyimgren/blob/master/CHANGES.txt
Project-URL: Issues, https://github.com/s-ball/pyimgren/issues
Project-URL: Source, https://github.com/s-ball/pyimgren
Author-email: s-ball <s-ball@laposte.net>
License-Expression: MIT
License-File: LICENSE.txt
Classifier: Development Status :: 5 - Production/Stable
Classifier: Environment :: Console
Classifier: Intended Audience :: Developers
Classifier: Intended Audience :: End Users/Desktop
Classifier: License :: OSI Approved :: MIT License
Classifier: Operating System :: OS Independent
Classifier: Programming Language :: Python
Classifier: Programming Language :: Python :: 3.9
Classifier: Programming Language :: Python :: 3.10
Classifier: Programming Language :: Python :: 3.11
Classifier: Programming Language :: Python :: 3.12
Classifier: Programming Language :: Python :: 3.13
Classifier: Programming Language :: Python :: Implementation :: CPython
Classifier: Topic :: Multimedia :: Graphics
Requires-Python: >=3.9
Requires-Dist: i18nparse
Requires-Dist: piexif
Provides-Extra: docs
Requires-Dist: sphinx-intl; extra == 'docs'
Provides-Extra: test
Requires-Dist: pyfakefs; extra == 'test'
